odoo/addons/l10n_es_account_invoice_sequence/README.rst
odoo/addons/l10n_es_account_invoice_sequence/__init__.py
odoo/addons/l10n_es_account_invoice_sequence/__manifest__.py
odoo/addons/l10n_es_account_invoice_sequence/hooks.py
odoo/addons/l10n_es_account_invoice_sequence/data/sequence_data.xml
odoo/addons/l10n_es_account_invoice_sequence/i18n/bg.po
odoo/addons/l10n_es_account_invoice_sequence/i18n/ca.po
odoo/addons/l10n_es_account_invoice_sequence/i18n/es.po
odoo/addons/l10n_es_account_invoice_sequence/i18n/eu.po
odoo/addons/l10n_es_account_invoice_sequence/i18n/fr.po
odoo/addons/l10n_es_account_invoice_sequence/i18n/gl.po
odoo/addons/l10n_es_account_invoice_sequence/i18n/hr.po
odoo/addons/l10n_es_account_invoice_sequence/i18n/l10n_es_account_invoice_sequence.pot
odoo/addons/l10n_es_account_invoice_sequence/i18n/pt_BR.po
odoo/addons/l10n_es_account_invoice_sequence/i18n/sl.po
odoo/addons/l10n_es_account_invoice_sequence/models/__init__.py
odoo/addons/l10n_es_account_invoice_sequence/models/account_chart_template.py
odoo/addons/l10n_es_account_invoice_sequence/models/account_invoice.py
odoo/addons/l10n_es_account_invoice_sequence/models/account_journal.py
odoo/addons/l10n_es_account_invoice_sequence/models/ir_sequence.py
odoo/addons/l10n_es_account_invoice_sequence/readme/CONTRIBUTORS.rst
odoo/addons/l10n_es_account_invoice_sequence/readme/DESCRIPTION.rst
odoo/addons/l10n_es_account_invoice_sequence/readme/INSTALL.rst
odoo/addons/l10n_es_account_invoice_sequence/readme/USAGE.rst
odoo/addons/l10n_es_account_invoice_sequence/static/description/icon.png
odoo/addons/l10n_es_account_invoice_sequence/static/description/index.html
odoo/addons/l10n_es_account_invoice_sequence/tests/__init__.py
odoo/addons/l10n_es_account_invoice_sequence/tests/test_create_chart.py
odoo/addons/l10n_es_account_invoice_sequence/tests/test_invoice_sequence.py
odoo/addons/l10n_es_account_invoice_sequence/tests/test_other_chart.py
odoo12_addon_l10n_es_account_invoice_sequence-12.0.1.0.2.dist-info/METADATA
odoo12_addon_l10n_es_account_invoice_sequence-12.0.1.0.2.dist-info/WHEEL
odoo12_addon_l10n_es_account_invoice_sequence-12.0.1.0.2.dist-info/top_level.txt
odoo12_addon_l10n_es_account_invoice_sequence-12.0.1.0.2.dist-info/RECORD
